[
{
  "id": "case_51",
  "level_name": "Case 51: The Grave Death at the Graveyard (ความตายอันน่าหดหู่ ณ สุสาน)",
  "difficulty": 3,
  "story_intro": "นักสืบโลจิโกเห็นอิร์ราติโนตายและถูกฝังไปแล้วกับตา แต่ที่น่าตกใจกว่าคือ 'สาธุคุณ' ที่ต้องมากล่าวคำไว้อาลัยในงานศพ... ดันมาถูกฆ่าตายตามไปอีกคนในสุสานแห่งนี้!",
  "profiles": {
    "suspects": [
      { "name": "อาสโทรโลเจอร์ อะซูร์", "detail": "นักดูดาวผู้เต็มไปด้วยคำถามเกี่ยวกับเวลาและสถานที่เกิดของคุณ ส่วนสูง 5'6\", ถนัดขวา, ตาสีเฮเซล, ผมสีน้ำตาลอ่อน, ราศีกรกฎ" },
      { "name": "เอิร์ล เกรย์", "detail": "ผู้สืบเชื้อสายตระกูลชาชื่อดัง ไม่แจกลายเซ็นแต่แจกถุงชาฟรีถ้าขอ ส่วนสูง 5'9\", ถนัดขวา, ตาสีน้ำตาลอ่อน, ผมขาว, ราศีมังกร" },
      { "name": "มิกซ์ แทนเจอรีน", "detail": "ผู้พิสูจน์ว่า Non-binary ก็เป็นฆาตกรได้ เป็นทั้งคนขุดหลุมศพและผู้ต้องสงสัย ส่วนสูง 5'5\", ถนัดซ้าย, ตาสีเฮเซล, ผมบลอนด์, ราศีมีน" },
      { "name": "คริปโตซูโอโลจิสต์ คลาวด์", "detail": "ผู้รู้ทุกความเคลื่อนไหวของปีศาจเจอร์ซีย์และมนุษย์มอด ส่วนสูง 5'7\", ถนัดขวา, ตาสีเทา, ผมขาว, ราศีพิจิก" }
    ],
    "weapons": [
      { "name": "หม้อต้มขนาดใหญ่", "detail": "น้ำหนักมาก, ทำจากโลหะ จะเอามาฟาดหรือเอาไว้ต้มน้ำให้เหยียบจิบก็ได้" },
      { "name": "เครื่องตรวจจับวิญญาณ", "detail": "น้ำหนักปานกลาง, โลหะผสมเทคโนโลยี ตรวจผีไม่ค่อยได้แต่ใช้ช็อตคนได้ดี" },
      { "name": "ไม้กวาด", "detail": "น้ำหนักปานกลาง, ทำจากไม้และฟาง เขาว่าแม่มดใช้ขี่ แต่โลจิโกใช้กวาดพื้น" },
      { "name": "แขนโครงกระดูก", "detail": "น้ำหนักปานกลาง, ทำจากกระดูก สังหารคนเป็นด้วยกระดูกของคนตาย" }
    ],
    "locations": [
      { "name": "กระท่อมประหลาด", "detail": "ในร่ม, กระท่อมไม้ตรงมุมสุสานที่คุณก็รู้ว่ามันมีความลับซ่อนอยู่" },
      { "name": "ร้านขายของที่ระลึก", "detail": "ในร่ม, มีของกระจุกกระจิกอย่างป้ายหลุมศพจำลองและตุ๊กตาหัวกะโหลกขาย" },
      { "name": "สุสานหินขนาดมหึมา", "detail": "ในร่ม, สุสานรูปพีระมิดสำหรับสมาชิกครอบครัวเศรษฐีเท่านั้น" },
      { "name": "ประตูทางเข้า", "detail": "กลางแจ้ง, ประตูเหล็กดัดขนาดใหญ่ที่มีคราบสนิมกำลังดี ให้บรรยากาศน่าขนลุก" }
    ],
    "motives": [
      { "name": "เพื่อปล้นเหยื่อ", "detail": "ต้องการทรัพย์สินของสาธุคุณ" },
      { "name": "เพื่อดูว่าตัวเองจะทำได้ไหม", "detail": "ความอยากรู้อยากลองอันดำมืด" },
      { "name": "เพื่อซ่อนความลับเรื่องชู้สาว", "detail": "ปกปิดความสัมพันธ์ที่บอกใครไม่ได้" },
      { "name": "เพื่อขโมยศพ", "detail": "ภารกิจลับในการเคลื่อนย้ายร่างไร้วิญญาณ" }
    ]
  },
  "categories": [
    { "id": "suspects", "name": "ผู้ต้องสงสัย", "items": ["อาสโทรโลเจอร์ อะซูร์", "เอิร์ล เกรย์", "มิกซ์ แทนเจอรีน", "คริปโตซูโอโลจิสต์ คลาวด์"] },
    { "id": "weapons", "name": "อาวุธ", "items": ["หม้อต้มขนาดใหญ่", "เครื่องตรวจจับวิญญาณ", "ไม้กวาด", "แขนโครงกระดูก"] },
    { "id": "locations", "name": "สถานที่", "items": ["กระท่อมประหลาด", "ร้านขายของที่ระลึก", "สุสานหินขนาดมหึมา", "ประตูทางเข้า"] },
    { "id": "motives", "name": "แรงจูงใจ", "items": ["เพื่อปล้นเหยื่อ", "เพื่อดูว่าตัวเองจะทำได้ไหม", "เพื่อซ่อนความลับเรื่องชู้สาว", "เพื่อขโมยศพ"] }
  ],
  "clues": [
    "อาสโทรโลเจอร์ อะซูร์ ไม่ได้นำไม้กวาดมาด้วย",
    "เอิร์ล เกรย์ จะไม่ฆ่าเพื่อลองทำดู หรือเพื่อซ่อนเรื่องชู้สาว",
    "พบเครื่องตรวจจับวิญญาณขัดอยู่ที่กรงเหล็กดัดของประตูทางเข้า",
    "พบขนไม้กวาดหนึ่งเส้นตกอยู่ข้าง ๆ ตุ๊กตาหัวกะโหลกในร้านขายของ",
    "คนที่ถือแขนโครงกระดูกกำลังพยายามซ่อนความลับเรื่องชู้สาว",
    "มิกซ์ แทนเจอรีน อยากจะขโมยศพมานานแล้ว",
    "คนที่แบกหม้อต้มขนาดใหญ่ต้องการจะปล้นสาธุคุณ",
    "มีคนเห็นคริปโตซูโอโลจิสต์ คลาวด์ อยู่ในกระท่อมประหลาด",
    "พบศพผู้เคราะห์ร้ายอยู่ภายในพีระมิดยักษ์ (สุสานหินขนาดมหึมา)"
  ],
  "testimonies": [],
  "solution_grid": [
    { "suspects": "เอิร์ล เกรย์", "weapons": "หม้อต้มขนาดใหญ่", "locations": "สุสานหินขนาดมหึมา", "motives": "เพื่อปล้นเหยื่อ" },
    { "suspects": "มิกซ์ แทนเจอรีน", "weapons": "ไม้กวาด", "locations": "ร้านขายของที่ระลึก", "motives": "เพื่อขโมยศพ" },
    { "suspects": "อาสโทรโลเจอร์ อะซูร์", "weapons": "เครื่องตรวจจับวิญญาณ", "locations": "ประตูทางเข้า", "motives": "เพื่อดูว่าตัวเองจะทำได้ไหม" },
    { "suspects": "คริปโตซูโอโลจิสต์ คลาวด์", "weapons": "แขนโครงกระดูก", "locations": "กระท่อมประหลาด", "motives": "เพื่อซ่อนความลับเรื่องชู้สาว" }
  ],
  "correct_accusation": {
    "suspect": "เอิร์ล เกรย์",
    "weapon": "หม้อต้มขนาดใหญ่",
    "location": "สุสานหินขนาดมหึมา",
    "motive": "เพื่อปล้นเหยื่อ"
  }
}
]
